LICENSE
MANIFEST.in
README.md
requirements.txt
setup.py
test-requirements.txt
tox.ini
doc/.DS_Store
doc/README.md
doc/client.md
doc/http-request.md
doc/http-response.md
doc/utility-classes.md
doc/controllers/database.md
doc/controllers/group.md
doc/controllers/metadata.md
doc/controllers/session.md
doc/controllers/user.md
doc/models/access-enum.md
doc/models/access-level-input.md
doc/models/analyst-onboarding-complete-enum.md
doc/models/api-rest-v2-database-table-create-request.md
doc/models/api-rest-v2-database-table-runquery-request.md
doc/models/api-rest-v2-group-addgroup-request.md
doc/models/api-rest-v2-group-addprivilege-request.md
doc/models/api-rest-v2-group-adduser-request.md
doc/models/api-rest-v2-group-create-request.md
doc/models/api-rest-v2-group-removegroup-request.md
doc/models/api-rest-v2-group-removeprivilege-request.md
doc/models/api-rest-v2-group-removeuser-request.md
doc/models/api-rest-v2-group-search-request.md
doc/models/api-rest-v2-group-update-request.md
doc/models/api-rest-v2-metadata-dependency-request.md
doc/models/api-rest-v2-metadata-favorite-assign-request.md
doc/models/api-rest-v2-metadata-favorite-unassign-request.md
doc/models/api-rest-v2-metadata-header-search-request.md
doc/models/api-rest-v2-metadata-homeliveboard-assign-request.md
doc/models/api-rest-v2-metadata-homeliveboard-unassign-request.md
doc/models/api-rest-v2-metadata-tag-assign-request.md
doc/models/api-rest-v2-metadata-tag-create-request.md
doc/models/api-rest-v2-metadata-tag-unassign-request.md
doc/models/api-rest-v2-metadata-tag-update-request.md
doc/models/api-rest-v2-metadata-tml-export-request.md
doc/models/api-rest-v2-metadata-tml-import-request.md
doc/models/api-rest-v2-session-gettoken-request.md
doc/models/api-rest-v2-session-login-request.md
doc/models/api-rest-v2-user-addgroup-request.md
doc/models/api-rest-v2-user-create-request.md
doc/models/api-rest-v2-user-removegroup-request.md
doc/models/api-rest-v2-user-search-request.md
restapisdktest.egg-info/PKG-INFO
restapisdktest.egg-info/SOURCES.txt
restapisdktest.egg-info/dependency_links.txt
restapisdktest.egg-info/requires.txt
restapisdktest.egg-info/top_level.txt
