Metadata-Version: 2.1
Name: restapisdktest
Version: 1.6.8
Summary: Python client library for RESTAPI SDK
Home-page: https://github.com/thoughtspot/rest-api-sdk/tree/main/Python
Author: ThoughtSpot
Author-email: support@thoughtspot.com
License: UNKNOWN
Platform: UNKNOWN
